js_lib_editor_js/__init__.py
js_lib_editor_js/apps.py
js_lib_editor_js/static/editorjs/checklist.js
js_lib_editor_js/static/editorjs/code.js
js_lib_editor_js/static/editorjs/delimiter.js
js_lib_editor_js/static/editorjs/editorjs-drag-drop.js
js_lib_editor_js/static/editorjs/editorjs-text-alignment-blocktune.js
js_lib_editor_js/static/editorjs/editorjs-undo.js
js_lib_editor_js/static/editorjs/editorjs.js
js_lib_editor_js/static/editorjs/embed.js
js_lib_editor_js/static/editorjs/header.js
js_lib_editor_js/static/editorjs/image.js
js_lib_editor_js/static/editorjs/inline-code.js
js_lib_editor_js/static/editorjs/link.js
js_lib_editor_js/static/editorjs/list.js
js_lib_editor_js/static/editorjs/marker.js
js_lib_editor_js/static/editorjs/paragraph.js
js_lib_editor_js/static/editorjs/quote.js
js_lib_editor_js/static/editorjs/raw.js
js_lib_editor_js/static/editorjs/table.js
js_lib_editor_js/static/editorjs/warning.js
django_js_lib_editor_js-2.29.1.1.dist-info/LICENSE
django_js_lib_editor_js-2.29.1.1.dist-info/WHEEL
django_js_lib_editor_js-2.29.1.1.dist-info/METADATA
django_js_lib_editor_js-2.29.1.1.dist-info/RECORD
