Metadata-Version: 2.1
Name: django-js-lib-editor-js
Version: 2.29.1.1
Summary: Editor JS Repackaged for Django
Classifier: License :: OSI Approved :: Apache Software License
